{
  "events":[
    {
      "title":"Open discussion : Effective activism part 1 By Christine Perc",
      "description":"",
      "start_datetime":"2020-04-14 10:00:00",
      "end_datetime":"2020-04-14 12:00:00",
      "address":"Zoom Meeting - Online ",
      "hosts":"Animal Resistance",
      "url":"https://www.facebook.com/events/279011596438081/"
    },
    {
      "title":"How Vegans Can Improve Relationships and Communication by Dr. Melanie Joy",
      "description":"",
      "start_datetime":"2020-04-17 08:00:00",
      "end_datetime":"2020-04-17 09:30:00",
      "address":"Zoom Meeting - Online ",
      "hosts":"Animal Resistance, Beyond Carnism, Center for Effective Vegan Advocacy",
      "url":"https://www.facebook.com/events/519767898733134/"
    },
    {
      "title":"Demo empathic listening with Joyce Van Camp",
      "description":"",
      "start_datetime":"2020-04-18 05:00:00",
      "end_datetime":"2020-04-18 06:30:00",
      "address":"More",
      "hosts":"Animal Resistance",
      "url":"https://www.facebook.com/events/558805895016646/"
    },
    {
      "title":"Animal Liberation Online Assembly - Kickoff!",
      "description":"",
      "start_datetime":"2020-04-18 13:00:00",
      "end_datetime":"2020-04-18 19:00:00",
      "address":"Online ",
      "hosts":"Animal Liberation Conference, Berkeley Organization for Animal Advocacy - BOAA, Direct Action Everywhere - DxE",
      "url":"https://www.facebook.com/events/2411771499061555/"
    },
    {
      "title":"Open discussion: Effective Activism Part 2 By Christine Perc",
      "description":"",
      "start_datetime":"2020-04-21 10:00:00",
      "end_datetime":"2020-04-21 12:00:00",
      "address":"More",
      "hosts":"Animal Resistance",
      "url":"https://www.facebook.com/events/1333616800164373/"
    },
    {
      "title":"Earth Day Virtual Rally",
      "description":"",
      "start_datetime":"2020-04-22 16:00:00",
      "end_datetime":"2020-04-22 18:00:00",
      "address":"Live streaming on Zoom and YouTube ",
      "hosts":"350PDX, Asian Pacific American Network of Oregon - APANO, OPAL Environmental Justice Oregon",
      "url":"https://www.facebook.com/events/239883970487533/"
    },
    {
      "title":"Climate Healers Health Conference",
      "description":"",
      "start_datetime":"2020-04-25 08:15:00",
      "end_datetime":"2020-04-25 18:30:00",
      "address":"Tickets \u00b7 $55 - $75 www.eventbrite.com",
      "hosts":"Marz Nutritionals",
      "url":"https://www.facebook.com/events/182784206253794/"
    },
    {
      "title":"Money Vs. Animal Rights - Open discussion by Glenn WRL",
      "description":"",
      "start_datetime":"2020-04-16 10:00:00",
      "end_datetime":"2020-04-16 12:00:00",
      "address":"More",
      "hosts":"Animal Resistance",
      "url":"https://www.facebook.com/events/2864831260259198/"
    },
    {
      "title":"Insect Suffering by Stijn Breurs",
      "description":"",
      "start_datetime":"2020-04-13 10:00:00",
      "end_datetime":"2020-04-13 12:00:00",
      "address":"More",
      "hosts":"Animal Resistance",
      "url":"https://www.facebook.com/events/1537023213139305/"
    }
  ]
}